rda_s3/__init__.py
rda_s3/rda_s3.py
ncar_rda_s3-0.1.3.dist-info/LICENSE
ncar_rda_s3-0.1.3.dist-info/METADATA
ncar_rda_s3-0.1.3.dist-info/WHEEL
ncar_rda_s3-0.1.3.dist-info/top_level.txt
ncar_rda_s3-0.1.3.dist-info/RECORD
