Metadata-Version: 2.1
Name: ncar-rda-s3
Version: 0.1.3
Summary: NCAR RDA S3 object storage utility
Home-page: https://github.com/NCAR/rda-s3
Author: NCAR RDA Team
Author-email: rdahelp@ucar.edu
License: UNKNOWN
Platform: UNKNOWN
Classifier: Development Status :: 2 - Pre-Alpha
Classifier: License :: OSI Approved :: MIT License
Classifier: Operating System :: POSIX
Classifier: Programming Language :: Python :: 3
Classifier: Programming Language :: Python :: 3.4
Classifier: Programming Language :: Python :: 3.5
Classifier: Programming Language :: Python :: 3.6
Classifier: Programming Language :: Python :: 3.7
Classifier: Topic :: Software Development :: Libraries :: Python Modules
Classifier: Intended Audience :: Developers
Requires-Python: >=3.1
Requires-Dist: boto3
Requires-Dist: botocore
